django_vrsns/__init__.py
django_vrsns/urls.py
django_vrsns/views.py
django_vrsns-0.3.0.dist-info/METADATA
django_vrsns-0.3.0.dist-info/WHEEL
django_vrsns-0.3.0.dist-info/RECORD
