Metadata-Version: 2.1
Name: django-vrsns
Version: 0.3.0
Summary: Provide an Django view that lists installed package versions
Author: Birger Schacht
Author-email: birger@rantanplan.org
Requires-Python: >=3.11,<4.0
Classifier: Programming Language :: Python :: 3
Classifier: Programming Language :: Python :: 3.11
Classifier: Programming Language :: Python :: 3.12
